{"inputs":{"node_modules/uptick-demo-site/dist/uptick-demo-site.js":{"bytes":2657,"imports":[],"format":"cjs"},"node_modules/uptick-demo-site/index.js":{"bytes":56,"imports":[{"path":"node_modules/uptick-demo-site/dist/uptick-demo-site.js","kind":"require-call","original":"./dist/uptick-demo-site.js"}],"format":"cjs"},"node_modules/react/cjs/react.development.js":{"bytes":87574,"imports":[],"format":"cjs"},"node_modules/react/index.js":{"bytes":190,"imports":[{"path":"node_modules/react/cjs/react.development.js","kind":"require-call","original":"./cjs/react.development.js"}],"format":"cjs"},"node_modules/scheduler/cjs/scheduler.development.js":{"bytes":17497,"imports":[],"format":"cjs"},"node_modules/scheduler/index.js":{"bytes":198,"imports":[{"path":"node_modules/scheduler/cjs/scheduler.development.js","kind":"require-call","original":"./cjs/scheduler.development.js"}],"format":"cjs"},"node_modules/react-dom/cjs/react-dom.development.js":{"bytes":1026501,"imports":[{"path":"node_modules/react/index.js","kind":"require-call","original":"react"},{"path":"node_modules/scheduler/index.js","kind":"require-call","original":"scheduler"}],"format":"cjs"},"node_modules/react-dom/index.js":{"bytes":1363,"imports":[{"path":"node_modules/react-dom/cjs/react-dom.development.js","kind":"require-call","original":"./cjs/react-dom.development.js"}],"format":"cjs"},"../dist/index.js":{"bytes":151622,"imports":[{"path":"node_modules/react/index.js","kind":"import-statement","original":"react"},{"path":"node_modules/react/index.js","kind":"import-statement","original":"react"},{"path":"node_modules/react/index.js","kind":"import-statement","original":"react"},{"path":"node_modules/react/index.js","kind":"import-statement","original":"react"},{"path":"node_modules/react/index.js","kind":"import-statement","original":"react"},{"path":"node_modules/react/index.js","kind":"import-statement","original":"react"},{"path":"node_modules/react/index.js","kind":"import-statement","original":"react"},{"path":"node_modules/react/index.js","kind":"import-statement","original":"react"},{"path":"node_modules/react/index.js","kind":"import-statement","original":"react"},{"path":"node_modules/react/index.js","kind":"import-statement","original":"react"},{"path":"node_modules/react/index.js","kind":"import-statement","original":"react"},{"path":"node_modules/react/index.js","kind":"import-statement","original":"react"},{"path":"node_modules/react/index.js","kind":"import-statement","original":"react"},{"path":"node_modules/react/index.js","kind":"import-statement","original":"react"},{"path":"node_modules/react/index.js","kind":"import-statement","original":"react"},{"path":"node_modules/react/index.js","kind":"import-statement","original":"react"},{"path":"node_modules/react/index.js","kind":"import-statement","original":"react"},{"path":"node_modules/react/index.js","kind":"import-statement","original":"react"},{"path":"node_modules/react/index.js","kind":"import-statement","original":"react"},{"path":"node_modules/react/index.js","kind":"import-statement","original":"react"},{"path":"node_modules/react/index.js","kind":"import-statement","original":"react"},{"path":"node_modules/react/index.js","kind":"import-statement","original":"react"},{"path":"node_modules/react/index.js","kind":"import-statement","original":"react"},{"path":"node_modules/react/index.js","kind":"import-statement","original":"react"},{"path":"node_modules/react/index.js","kind":"import-statement","original":"react"},{"path":"node_modules/react/index.js","kind":"import-statement","original":"react"},{"path":"node_modules/react/index.js","kind":"import-statement","original":"react"},{"path":"node_modules/react/index.js","kind":"import-statement","original":"react"},{"path":"node_modules/react/index.js","kind":"import-statement","original":"react"},{"path":"node_modules/react/index.js","kind":"import-statement","original":"react"},{"path":"node_modules/react/index.js","kind":"import-statement","original":"react"},{"path":"node_modules/react/index.js","kind":"import-statement","original":"react"},{"path":"node_modules/react/index.js","kind":"import-statement","original":"react"},{"path":"node_modules/react/index.js","kind":"import-statement","original":"react"},{"path":"node_modules/react/index.js","kind":"import-statement","original":"react"},{"path":"node_modules/react/index.js","kind":"import-statement","original":"react"},{"path":"node_modules/react/index.js","kind":"import-statement","original":"react"},{"path":"node_modules/react/index.js","kind":"import-statement","original":"react"},{"path":"node_modules/react/index.js","kind":"import-statement","original":"react"},{"path":"node_modules/react/index.js","kind":"import-statement","original":"react"},{"path":"node_modules/react/index.js","kind":"import-statement","original":"react"},{"path":"node_modules/react/index.js","kind":"import-statement","original":"react"},{"path":"node_modules/react/index.js","kind":"import-statement","original":"react"},{"path":"node_modules/react/index.js","kind":"import-statement","original":"react"},{"path":"node_modules/react/index.js","kind":"import-statement","original":"react"},{"path":"node_modules/react/index.js","kind":"import-statement","original":"react"},{"path":"node_modules/react/index.js","kind":"import-statement","original":"react"},{"path":"node_modules/react/index.js","kind":"import-statement","original":"react"},{"path":"node_modules/react/index.js","kind":"import-statement","original":"react"},{"path":"node_modules/react/index.js","kind":"import-statement","original":"react"},{"path":"node_modules/react/index.js","kind":"import-statement","original":"react"},{"path":"node_modules/react/index.js","kind":"import-statement","original":"react"},{"path":"node_modules/react/index.js","kind":"import-statement","original":"react"}],"format":"esm"},"src/sample-form.tsx":{"bytes":8786,"imports":[{"path":"node_modules/react/index.js","kind":"import-statement","original":"react"},{"path":"node_modules/react-dom/index.js","kind":"import-statement","original":"react-dom"},{"path":"../dist/index.js","kind":"import-statement","original":"bootstrap-mireco"}],"format":"esm"},"src/demo.ts":{"bytes":75,"imports":[{"path":"node_modules/uptick-demo-site/index.js","kind":"import-statement","original":"uptick-demo-site"},{"path":"src/sample-form.tsx","kind":"import-statement","original":"./sample-form.js"}],"format":"esm"},"stylus:/Users/borchael/Projects/bootstrap-mireco/demo/src/demo.styl":{"bytes":203884,"imports":[{"path":"data:image/svg+xml,%3csvg xmlns='http://www.w3.org/2000/svg' viewBox='0 0 8 8'%3e%3cpath fill='%2328a745' d='M2.3 6.73L.6 4.53c-.4-1.04.46-1.4 1.1-.8l1.1 1.4 3.4-3.8c.6-.63 1.6-.27 1.2.7l-4 4.6c-.43.5-.8.4-1.1.1z'/%3e%3c/svg%3e","kind":"url-token","external":true},{"path":"data:image/svg+xml,%3csvg xmlns='http://www.w3.org/2000/svg' viewBox='0 0 4 5'%3e%3cpath fill='%23343a40' d='M2 0L0 2h4zm0 5L0 3h4z'/%3e%3c/svg%3e","kind":"url-token","external":true},{"path":"data:image/svg+xml,%3csvg xmlns='http://www.w3.org/2000/svg' viewBox='0 0 8 8'%3e%3cpath fill='%2328a745' d='M2.3 6.73L.6 4.53c-.4-1.04.46-1.4 1.1-.8l1.1 1.4 3.4-3.8c.6-.63 1.6-.27 1.2.7l-4 4.6c-.43.5-.8.4-1.1.1z'/%3e%3c/svg%3e","kind":"url-token","external":true},{"path":"data:image/svg+xml,%3csvg xmlns='http://www.w3.org/2000/svg' fill='%23dc3545' viewBox='-2 -2 7 7'%3e%3cpath stroke='%23d9534f' d='M0 0l3 3m0-3L0 3'/%3e%3ccircle r='.5'/%3e%3ccircle cx='3' r='.5'/%3e%3ccircle cy='3' r='.5'/%3e%3ccircle cx='3' cy='3' r='.5'/%3e%3c/svg%3E","kind":"url-token","external":true},{"path":"data:image/svg+xml,%3csvg xmlns='http://www.w3.org/2000/svg' viewBox='0 0 4 5'%3e%3cpath fill='%23343a40' d='M2 0L0 2h4zm0 5L0 3h4z'/%3e%3c/svg%3e","kind":"url-token","external":true},{"path":"data:image/svg+xml,%3csvg xmlns='http://www.w3.org/2000/svg' fill='%23dc3545' viewBox='-2 -2 7 7'%3e%3cpath stroke='%23d9534f' d='M0 0l3 3m0-3L0 3'/%3e%3ccircle r='.5'/%3e%3ccircle cx='3' r='.5'/%3e%3ccircle cy='3' r='.5'/%3e%3ccircle cx='3' cy='3' r='.5'/%3e%3c/svg%3E","kind":"url-token","external":true},{"path":"data:image/svg+xml,%3csvg xmlns='http://www.w3.org/2000/svg' viewBox='0 0 8 8'%3e%3cpath fill='%23fff' d='M6.564.75l-3.59 3.612-1.538-1.55L0 4.26 2.974 7.25 8 2.193z'/%3e%3c/svg%3e","kind":"url-token","external":true},{"path":"data:image/svg+xml,%3csvg xmlns='http://www.w3.org/2000/svg' viewBox='0 0 4 4'%3e%3cpath stroke='%23fff' d='M0 2h4'/%3e%3c/svg%3e","kind":"url-token","external":true},{"path":"data:image/svg+xml,%3csvg xmlns='http://www.w3.org/2000/svg' viewBox='-4 -4 8 8'%3e%3ccircle r='3' fill='%23fff'/%3e%3c/svg%3e","kind":"url-token","external":true},{"path":"data:image/svg+xml,%3csvg xmlns='http://www.w3.org/2000/svg' viewBox='0 0 4 5'%3e%3cpath fill='%23343a40' d='M2 0L0 2h4zm0 5L0 3h4z'/%3e%3c/svg%3e","kind":"url-token","external":true},{"path":"data:image/svg+xml,%3csvg viewBox='0 0 30 30' xmlns='http://www.w3.org/2000/svg'%3e%3cpath stroke='rgba(0, 0, 0, 0.5)' stroke-width='2' stroke-linecap='round' stroke-miterlimit='10' d='M4 7h22M4 15h22M4 23h22'/%3e%3c/svg%3e","kind":"url-token","external":true},{"path":"data:image/svg+xml,%3csvg viewBox='0 0 30 30' xmlns='http://www.w3.org/2000/svg'%3e%3cpath stroke='rgba(255, 255, 255, 0.5)' stroke-width='2' stroke-linecap='round' stroke-miterlimit='10' d='M4 7h22M4 15h22M4 23h22'/%3e%3c/svg%3e","kind":"url-token","external":true},{"path":"data:image/svg+xml,%3csvg xmlns='http://www.w3.org/2000/svg' fill='%23fff' viewBox='0 0 8 8'%3e%3cpath d='M5.25 0l-4 4 4 4 1.5-1.5-2.5-2.5 2.5-2.5-1.5-1.5z'/%3e%3c/svg%3e","kind":"url-token","external":true},{"path":"data:image/svg+xml,%3csvg xmlns='http://www.w3.org/2000/svg' fill='%23fff' viewBox='0 0 8 8'%3e%3cpath d='M2.75 0l-1.5 1.5 2.5 2.5-2.5 2.5 1.5 1.5 4-4-4-4z'/%3e%3c/svg%3e","kind":"url-token","external":true}]}},"outputs":{"dist/demo.js":{"imports":[],"exports":[],"entryPoint":"src/demo.ts","inputs":{"node_modules/uptick-demo-site/dist/uptick-demo-site.js":{"bytesInOutput":2961},"node_modules/uptick-demo-site/index.js":{"bytesInOutput":174},"node_modules/react/cjs/react.development.js":{"bytesInOutput":80794},"node_modules/react/index.js":{"bytesInOutput":247},"node_modules/scheduler/cjs/scheduler.development.js":{"bytesInOutput":17789},"node_modules/scheduler/index.js":{"bytesInOutput":259},"node_modules/react-dom/cjs/react-dom.development.js":{"bytesInOutput":948782},"node_modules/react-dom/index.js":{"bytesInOutput":279},"src/demo.ts":{"bytesInOutput":109},"src/sample-form.tsx":{"bytesInOutput":10725},"../dist/index.js":{"bytesInOutput":212125}},"bytes":1277918},"dist/demo.css":{"imports":[{"path":"data:image/svg+xml,%3csvg xmlns='http://www.w3.org/2000/svg' viewBox='0 0 8 8'%3e%3cpath fill='%2328a745' d='M2.3 6.73L.6 4.53c-.4-1.04.46-1.4 1.1-.8l1.1 1.4 3.4-3.8c.6-.63 1.6-.27 1.2.7l-4 4.6c-.43.5-.8.4-1.1.1z'/%3e%3c/svg%3e","kind":"url-token","external":true},{"path":"data:image/svg+xml,%3csvg xmlns='http://www.w3.org/2000/svg' viewBox='0 0 4 5'%3e%3cpath fill='%23343a40' d='M2 0L0 2h4zm0 5L0 3h4z'/%3e%3c/svg%3e","kind":"url-token","external":true},{"path":"data:image/svg+xml,%3csvg xmlns='http://www.w3.org/2000/svg' viewBox='0 0 8 8'%3e%3cpath fill='%2328a745' d='M2.3 6.73L.6 4.53c-.4-1.04.46-1.4 1.1-.8l1.1 1.4 3.4-3.8c.6-.63 1.6-.27 1.2.7l-4 4.6c-.43.5-.8.4-1.1.1z'/%3e%3c/svg%3e","kind":"url-token","external":true},{"path":"data:image/svg+xml,%3csvg xmlns='http://www.w3.org/2000/svg' fill='%23dc3545' viewBox='-2 -2 7 7'%3e%3cpath stroke='%23d9534f' d='M0 0l3 3m0-3L0 3'/%3e%3ccircle r='.5'/%3e%3ccircle cx='3' r='.5'/%3e%3ccircle cy='3' r='.5'/%3e%3ccircle cx='3' cy='3' r='.5'/%3e%3c/svg%3E","kind":"url-token","external":true},{"path":"data:image/svg+xml,%3csvg xmlns='http://www.w3.org/2000/svg' viewBox='0 0 4 5'%3e%3cpath fill='%23343a40' d='M2 0L0 2h4zm0 5L0 3h4z'/%3e%3c/svg%3e","kind":"url-token","external":true},{"path":"data:image/svg+xml,%3csvg xmlns='http://www.w3.org/2000/svg' fill='%23dc3545' viewBox='-2 -2 7 7'%3e%3cpath stroke='%23d9534f' d='M0 0l3 3m0-3L0 3'/%3e%3ccircle r='.5'/%3e%3ccircle cx='3' r='.5'/%3e%3ccircle cy='3' r='.5'/%3e%3ccircle cx='3' cy='3' r='.5'/%3e%3c/svg%3E","kind":"url-token","external":true},{"path":"data:image/svg+xml,%3csvg xmlns='http://www.w3.org/2000/svg' viewBox='0 0 8 8'%3e%3cpath fill='%23fff' d='M6.564.75l-3.59 3.612-1.538-1.55L0 4.26 2.974 7.25 8 2.193z'/%3e%3c/svg%3e","kind":"url-token","external":true},{"path":"data:image/svg+xml,%3csvg xmlns='http://www.w3.org/2000/svg' viewBox='0 0 4 4'%3e%3cpath stroke='%23fff' d='M0 2h4'/%3e%3c/svg%3e","kind":"url-token","external":true},{"path":"data:image/svg+xml,%3csvg xmlns='http://www.w3.org/2000/svg' viewBox='-4 -4 8 8'%3e%3ccircle r='3' fill='%23fff'/%3e%3c/svg%3e","kind":"url-token","external":true},{"path":"data:image/svg+xml,%3csvg xmlns='http://www.w3.org/2000/svg' viewBox='0 0 4 5'%3e%3cpath fill='%23343a40' d='M2 0L0 2h4zm0 5L0 3h4z'/%3e%3c/svg%3e","kind":"url-token","external":true},{"path":"data:image/svg+xml,%3csvg viewBox='0 0 30 30' xmlns='http://www.w3.org/2000/svg'%3e%3cpath stroke='rgba(0, 0, 0, 0.5)' stroke-width='2' stroke-linecap='round' stroke-miterlimit='10' d='M4 7h22M4 15h22M4 23h22'/%3e%3c/svg%3e","kind":"url-token","external":true},{"path":"data:image/svg+xml,%3csvg viewBox='0 0 30 30' xmlns='http://www.w3.org/2000/svg'%3e%3cpath stroke='rgba(255, 255, 255, 0.5)' stroke-width='2' stroke-linecap='round' stroke-miterlimit='10' d='M4 7h22M4 15h22M4 23h22'/%3e%3c/svg%3e","kind":"url-token","external":true},{"path":"data:image/svg+xml,%3csvg xmlns='http://www.w3.org/2000/svg' fill='%23fff' viewBox='0 0 8 8'%3e%3cpath d='M5.25 0l-4 4 4 4 1.5-1.5-2.5-2.5 2.5-2.5-1.5-1.5z'/%3e%3c/svg%3e","kind":"url-token","external":true},{"path":"data:image/svg+xml,%3csvg xmlns='http://www.w3.org/2000/svg' fill='%23fff' viewBox='0 0 8 8'%3e%3cpath d='M2.75 0l-1.5 1.5 2.5 2.5-2.5 2.5 1.5 1.5 4-4-4-4z'/%3e%3c/svg%3e","kind":"url-token","external":true}],"entryPoint":"stylus:/Users/borchael/Projects/bootstrap-mireco/demo/src/demo.styl","inputs":{"stylus:/Users/borchael/Projects/bootstrap-mireco/demo/src/demo.styl":{"bytesInOutput":204952}},"bytes":205242}}}